{
  "0": "Timestamp#1000#Action#SelectedAnswer#1",
  "1": "Timestamp#1470#Action#Submit#0",
  "2": "Timestamp#1822#Action#SelectedAnswer#4",
  "3": "Timestamp#2068#Action#Submit#1",
  "4": "Timestamp#2317#Action#SelectedAnswer#4",
  "5": "Timestamp#2550#Action#Submit#2",
  "6": "Timestamp#2751#Action#SelectedAnswer#3",
  "7": "Timestamp#3251#Action#Submit#3",
  "8": "Timestamp#103665#Action#Submit#4",
  "9": "Timestamp#104027#Action#Submit#5",
  "10": "Timestamp#104240#Action#Submit#6",
  "11": "Timestamp#104457#Action#Submit#7",
  "12": "Timestamp#104635#Action#Submit#8",
  "13": "Timestamp#104816#Action#Submit#9",
  "14": "Timestamp#104986#Action#Submit#10",
  "15": "Timestamp#105176#Action#Submit#11",
  "16": "Timestamp#105346#Action#Submit#12",
  "17": "Timestamp#105646#Action#Submit#13",
  "18": "Timestamp#105804#Action#Submit#14",
  "19": "Timestamp#105989#Action#Submit#15",
  "20": "Timestamp#106145#Action#Submit#16",
  "21": "Timestamp#106323#Action#Submit#17",
  "UserName": "\uc815\ud558",
  "UserNumber": "2",
  "TaskNum": "TestGroupA"
}